odoo8_addon_l10n_pt_account_asset-8.0.1.0.1.99.dev3-py2.7-nspkg.pth
odoo8_addon_l10n_pt_account_asset-8.0.1.0.1.99.dev3.dist-info/DESCRIPTION.rst
odoo8_addon_l10n_pt_account_asset-8.0.1.0.1.99.dev3.dist-info/METADATA
odoo8_addon_l10n_pt_account_asset-8.0.1.0.1.99.dev3.dist-info/RECORD
odoo8_addon_l10n_pt_account_asset-8.0.1.0.1.99.dev3.dist-info/WHEEL
odoo8_addon_l10n_pt_account_asset-8.0.1.0.1.99.dev3.dist-info/metadata.json
odoo8_addon_l10n_pt_account_asset-8.0.1.0.1.99.dev3.dist-info/namespace_packages.txt
odoo8_addon_l10n_pt_account_asset-8.0.1.0.1.99.dev3.dist-info/top_level.txt
odoo_addons/l10n_pt_account_asset/README.rst
odoo_addons/l10n_pt_account_asset/__init__.py
odoo_addons/l10n_pt_account_asset/__openerp__.py
odoo_addons/l10n_pt_account_asset/data/account_legal_rate.xml
odoo_addons/l10n_pt_account_asset/i18n/pt.po
odoo_addons/l10n_pt_account_asset/models/__init__.py
odoo_addons/l10n_pt_account_asset/models/account_asset_category.py
odoo_addons/l10n_pt_account_asset/models/account_asset_legal_rate.py
odoo_addons/l10n_pt_account_asset/security/ir.model.access.csv
odoo_addons/l10n_pt_account_asset/static/description/icon.png
odoo_addons/l10n_pt_account_asset/views/account_asset_category.xml
odoo_addons/l10n_pt_account_asset/views/account_legal_rate.xml
