Metadata-Version: 2.0
Name: odoo8-addon-l10n-pt-account-asset
Version: 8.0.1.0.1.99.dev3
Summary: Portuguese asset management localization
Home-page: https://github.com/OCA/l10n-portugal
Author: Sossia, Odoo Community Association (OCA)
Author-email: support@odoo-community.org
License: AGPL-3
Platform: UNKNOWN
Classifier: Programming Language :: Python
Classifier: Framework :: Odoo
Classifier: License :: OSI Approved :: GNU Affero General Public License v3
Requires-Python: ~=2.7
Requires-Dist: odoo (<9.0a,>=8.0a)
Requires-Dist: odoo8-addon-account-asset-management
